twoStepIntermittend/__init__.py
twoStepIntermittend/_modidx.py
twoStepIntermittend/core.py
twoStepIntermittend/twoStep.py
twoStepIntermittend-0.0.1.dist-info/LICENSE
twoStepIntermittend-0.0.1.dist-info/METADATA
twoStepIntermittend-0.0.1.dist-info/WHEEL
twoStepIntermittend-0.0.1.dist-info/entry_points.txt
twoStepIntermittend-0.0.1.dist-info/top_level.txt
twoStepIntermittend-0.0.1.dist-info/RECORD
